MANIFEST.in
RELEASE-VERSION
get_git_version.py
setup.py
bertha.egg-info/PKG-INFO
bertha.egg-info/SOURCES.txt
bertha.egg-info/dependency_links.txt
bertha.egg-info/entry_points.txt
bertha.egg-info/requires.txt
bertha.egg-info/top_level.txt
bertha.egg-info/zip-safe
src/__init__.py
src/client.py
src/main.py