Metadata-Version: 1.0
Name: bertha
Version: 0.1.0a1
Summary: Python client library and console util for BerthaD
Home-page: http://github.com/bwesterb/py-bertha/
Author: Bas Westerbaan
Author-email: bas@westerbaan.name
License: UNKNOWN
Platform: UNKNOWN
